bootstrap_modal_forms/__init__.py
bootstrap_modal_forms/forms.py
bootstrap_modal_forms/generic.py
bootstrap_modal_forms/mixins.py
bootstrap_modal_forms/static/js/bootstrap5.modal.forms.js
bootstrap_modal_forms/static/js/bootstrap5.modal.forms.min.js
bootstrap_modal_forms/static/js/jquery.bootstrap.modal.forms.js
bootstrap_modal_forms/static/js/jquery.bootstrap.modal.forms.min.js
examples/__init__.py
examples/apps.py
examples/forms.py
examples/models.py
examples/urls.py
examples/views.py
examples/migrations/0001_initial.py
examples/migrations/__init__.py
setup/__init__.py
setup/settings.py
setup/urls.py
setup/wsgi.py
tests/__init__.py
tests/base.py
tests/tests_functional.py
tests/tests_unit.py
django_bootstrap_modal_forms-3.0.4.dist-info/LICENSE.txt
django_bootstrap_modal_forms-3.0.4.dist-info/METADATA
django_bootstrap_modal_forms-3.0.4.dist-info/WHEEL
django_bootstrap_modal_forms-3.0.4.dist-info/top_level.txt
django_bootstrap_modal_forms-3.0.4.dist-info/RECORD
