Metadata-Version: 2.1
Name: django-bootstrap-modal-forms
Version: 3.0.4
Summary: A Django plugin for creating AJAX driven forms in Bootstrap modal.
Home-page: https://github.com/trco/django-bootstrap-modal-forms
Author: Uros Trstenjak
Author-email: uros.trstenjak@gmail.com
License: MIT License
Classifier: Development Status :: 5 - Production/Stable
Classifier: Framework :: Django
Classifier: Intended Audience :: Developers
Classifier: License :: OSI Approved :: MIT License
Classifier: Operating System :: OS Independent
Classifier: Programming Language :: Python :: 3.8
Classifier: Programming Language :: Python :: 3.9
Classifier: Programming Language :: Python :: 3.10
Classifier: Programming Language :: Python :: 3.11
Classifier: Topic :: Software Development :: Libraries :: Python Modules
License-File: LICENSE.txt
